steering_vectors-0.12.2.dist-info/METADATA
steering_vectors-0.12.2.dist-info/WHEEL
steering_vectors-0.12.2.dist-info/entry_points.txt
steering_vectors-0.12.2.dist-info/licenses/LICENSE
steering_vectors/__init__.py
steering_vectors/aggregators.py
steering_vectors/layer_matching.py
steering_vectors/record_activations.py
steering_vectors/steering_operators.py
steering_vectors/steering_vector.py
steering_vectors/token_utils.py
steering_vectors/torch_utils.py
steering_vectors/train_steering_vector.py
steering_vectors/utils.py
steering_vectors-0.12.2.dist-info/RECORD
