Metadata-Version: 2.1
Name: steering-vectors
Version: 0.12.2
Summary: Steering vectors for transformer language models in Pytorch / Huggingface
Author-Email: David Chanin <chanindav@gmail.com>, Daniel Tan <dtch009@gmail.com>
License: MIT
Project-URL: homepage, https://steering-vectors.github.io/steering-vectors
Project-URL: repository, https://github.com/steering-vectors/steering-vectors
Requires-Python: <4.0,>=3.10
Requires-Dist: transformers<5.0.0,>=4.35.2
Requires-Dist: tqdm<5.0.0,>=4.1.0
Requires-Dist: scikit-learn<2.0.0,>=1.4.0
